pymes/__init__.py
pymes/pymes.py
pymes-0.0.1.dist-info/METADATA
pymes-0.0.1.dist-info/WHEEL
pymes-0.0.1.dist-info/top_level.txt
pymes-0.0.1.dist-info/RECORD
