Metadata-Version: 2.1
Name: pymes
Version: 0.0.1
Summary: An educational python module to explore stochastic population dynamics.
Author-email: Ulrich Dobramysl <ulrich.dobramysl@gmail.com>
License: MIT
Keywords: population dynamics,simulations
Classifier: Programming Language :: Python :: 3
Requires-Python: >=3.8
Requires-Dist: numpy >=1.20.0
